vint/__init__.py
vint/asset.py
vint/bootstrap.py
vint/_bundles/__init__.py
vint/_bundles/vimlparser.py
vint/asset/default_config.yaml
vint/asset/void_config.yaml
vint/ast/__init__.py
vint/ast/node_type.py
vint/ast/parsing.py
vint/ast/traversing.py
vint/ast/dictionary/__init__.py
vint/ast/dictionary/abbreviations.py
vint/ast/dictionary/autocmd_events.py
vint/ast/dictionary/builtins.py
vint/ast/plugin/__init__.py
vint/ast/plugin/abstract_ast_plugin.py
vint/ast/plugin/builtin_identifiers.py
vint/ast/plugin/scope_plugin/__init__.py
vint/ast/plugin/scope_plugin/identifier_classifier.py
vint/ast/plugin/scope_plugin/map_and_filter_parser.py
vint/ast/plugin/scope_plugin/redir_assignment_parser.py
vint/ast/plugin/scope_plugin/reference_reachability_tester.py
vint/ast/plugin/scope_plugin/scope_detector.py
vint/ast/plugin/scope_plugin/scope_linker.py
vint/ast/plugin/scope_plugin/two_way_scope_reference_attacher.py
vint/compat/__init__.py
vint/compat/itertools/__init__.py
vint/compat/unittest/__init__.py
vint/encodings/__init__.py
vint/encodings/decoder.py
vint/encodings/decoding_strategy.py
vint/linting/__init__.py
vint/linting/cli.py
vint/linting/env.py
vint/linting/file_filter.py
vint/linting/level.py
vint/linting/linter.py
vint/linting/policy_registry.py
vint/linting/policy_set.py
vint/linting/config/__init__.py
vint/linting/config/config_cmdargs_source.py
vint/linting/config/config_comment_source.py
vint/linting/config/config_container.py
vint/linting/config/config_default_source.py
vint/linting/config/config_dict_source.py
vint/linting/config/config_file_source.py
vint/linting/config/config_filenames.py
vint/linting/config/config_global_source.py
vint/linting/config/config_project_source.py
vint/linting/config/config_source.py
vint/linting/config/config_util.py
vint/linting/formatter/__init__.py
vint/linting/formatter/formatter.py
vint/linting/formatter/json_formatter.py
vint/linting/formatter/statistic_formatter.py
vint/linting/policy/__init__.py
vim_vint-0.3.21.dist-info/LICENSE.txt
vim_vint-0.3.21.dist-info/METADATA
vim_vint-0.3.21.dist-info/WHEEL
vim_vint-0.3.21.dist-info/entry_points.txt
vim_vint-0.3.21.dist-info/top_level.txt
vim_vint-0.3.21.dist-info/RECORD
